tests/__init__.py
tests/mocks.py
tests/test_cli_functions.py
tests/test_compatability.py
tests/test_filters.py
tests/test_refresh.py
tests/test_time_is_stale.py
tests/test_video_mapping.py
tests/test_videos_list.py
tests/cli/__init__.py
tests/cli/test_cli_arguments.py
tests/cli/test_filter.py
tests/cli/test_refresh.py
yt_queue/__init__.py
yt_queue/__main__.py
yt_queue/cli.py
yt_queue/file.py
yt_queue/filters.py
yt_queue/internal/__init__.py
yt_queue/internal/mapper.py
yt_queue/internal/yt_dlp_wrapper.py
yt_queue/utils/__init__.py
yt_queue/utils/loggers.py
yt_queue/utils/time.py
yt_queue-0.13.1.dist-info/licenses/LICENSE
yt_queue-0.13.1.dist-info/METADATA
yt_queue-0.13.1.dist-info/WHEEL
yt_queue-0.13.1.dist-info/entry_points.txt
yt_queue-0.13.1.dist-info/top_level.txt
yt_queue-0.13.1.dist-info/RECORD
