Metadata-Version: 2.4
Name: yt-queue
Version: 0.13.1
Summary: CLI to keep track of videos in Youtube playlists
Author-email: Hendri Pretorius <pretorh@gmail.com>
Project-URL: Homepage, https://github.com/pretorh/yt-queue
Project-URL: Bug Tracker, https://github.com/pretorh/yt-queue/issues
Keywords: yt-dlp,YouTube
Classifier: Programming Language :: Python :: 3
Classifier: Operating System :: OS Independent
Requires-Python: >=3.10
License-File: LICENSE
Requires-Dist: yt-dlp==2026.01.29
Provides-Extra: dev
Requires-Dist: pylint==3.0.2; extra == "dev"
Requires-Dist: pytest==7.4.3; extra == "dev"
Requires-Dist: setuptools==78.1.1; extra == "dev"
Dynamic: license-file
